Metadata-Version: 1.1
Name: bolier-plate
Version: 1.1.0
Summary: Template already set
Home-page: https://github.com/alexxfernandez13/boiler_plate
Author: Alejandro Fernandez
Author-email: alexxfernandez@hotmail.es
License: UNKNOWN
Platform: UNKNOWN
Classifier: Programming Language :: Python :: 3
Classifier: License :: OSI Approved :: MIT License
Classifier: Operating System :: OS Independent
